<?xml version="1.0" encoding="utf-8" ?>
<dwsync>
<file name="AC_OETags.js" server="//FAUWEB6.fau.edu/nurnet/" local="129507528480000000" remote="129507528480000000" Dst="1" />
<file name="html5.html" server="//FAUWEB6.fau.edu/nurnet/" local="131661313680000000" remote="131661313680000000" Dst="1" />
<file name="html5.js" server="//FAUWEB6.fau.edu/nurnet/" local="130020879520000000" remote="130020879520000000" Dst="1" />
<file name="html5forms.html" server="//FAUWEB6.fau.edu/nurnet/" local="131025033600000000" remote="131025033600000000" Dst="1" />
<file name="html5forpc.html" server="//FAUWEB6.fau.edu/nurnet/" local="131038213620000000" remote="131038213620000000" Dst="1" />
<file name="html5forwebkit.html" server="//FAUWEB6.fau.edu/nurnet/" local="130444850000000000" remote="130444850000000000" Dst="1" />
<file name="html5forwebkit.js" server="//FAUWEB6.fau.edu/nurnet/" local="131006773380000000" remote="131006773380000000" Dst="1" />
<file name="html5ms.js" server="//FAUWEB6.fau.edu/nurnet/" local="131200829600000000" remote="131200829600000000" Dst="1" />
<file name="html5pc.js" server="//FAUWEB6.fau.edu/nurnet/" local="131200829500000000" remote="131200829500000000" Dst="1" />
<file name="index-h5.html" server="//FAUWEB6.fau.edu/nurnet/" local="131485963220000000" remote="131485963220000000" Dst="1" />
<file name="index.html" server="//FAUWEB6.fau.edu/nurnet/" local="132204656360000000" remote="132204656360000000" Dst="1" />
<file name="libgif.js" server="//FAUWEB6.fau.edu/nurnet/" local="130444985880000000" remote="130444985880000000" Dst="1" />
<file name="main.swf" server="//FAUWEB6.fau.edu/nurnet/" local="131198574980000000" remote="131198574980000000" Dst="1" />
<file name="playerProductInstall.swf" server="//FAUWEB6.fau.edu/nurnet/" local="129507528480000000" remote="129507528480000000" Dst="1" />
<file name="spin.min.js" server="//FAUWEB6.fau.edu/nurnet/" local="129586768620000000" remote="129586768620000000" Dst="1" />
<file name="index.html" server="//boc22web6.ad.fau.edu/nit/" local="132204656380000000" remote="132204620380000000" Dst="2" />
<file name="AC_OETags.js" server="//boc22web6.ad.fau.edu/nit/" local="129507492480000000" remote="129507492480000000" Dst="2" />
<file name="html5.html" server="//boc22web6.ad.fau.edu/nit/" local="131661277680000000" remote="131661277680000000" Dst="2" />
<file name="html5.js" server="//boc22web6.ad.fau.edu/nit/" local="130020843520000000" remote="130020843520000000" Dst="2" />
<file name="html5forms.html" server="//boc22web6.ad.fau.edu/nit/" local="131024997600000000" remote="131024997600000000" Dst="2" />
<file name="html5forpc.html" server="//boc22web6.ad.fau.edu/nit/" local="131038177620000000" remote="131038177620000000" Dst="2" />
<file name="html5forwebkit.html" server="//boc22web6.ad.fau.edu/nit/" local="130444814000000000" remote="130444814000000000" Dst="2" />
<file name="html5forwebkit.js" server="//boc22web6.ad.fau.edu/nit/" local="131006737380000000" remote="131006737380000000" Dst="2" />
<file name="html5ms.js" server="//boc22web6.ad.fau.edu/nit/" local="131200793600000000" remote="131200793600000000" Dst="2" />
<file name="html5pc.js" server="//boc22web6.ad.fau.edu/nit/" local="131200793500000000" remote="131200793500000000" Dst="2" />
<file name="index-h5.html" server="//boc22web6.ad.fau.edu/nit/" local="131485927220000000" remote="131485927220000000" Dst="2" />
<file name="libgif.js" server="//boc22web6.ad.fau.edu/nit/" local="130444949880000000" remote="130444949880000000" Dst="2" />
<file name="main.swf" server="//boc22web6.ad.fau.edu/nit/" local="131198538980000000" remote="131198538980000000" Dst="2" />
<file name="playerProductInstall.swf" server="//boc22web6.ad.fau.edu/nit/" local="129507492480000000" remote="129507492480000000" Dst="2" />
<file name="spin.min.js" server="//boc22web6.ad.fau.edu/nit/" local="129586732620000000" remote="129586732620000000" Dst="2" />
</dwsync>