<?xml version="1.0" encoding="utf-8" ?>
<dwsync>
<file name="allande.jpg" server="//boc22web6.ad.fau.edu/nit/" local="131975719400000000" remote="131975683400000000" Dst="2" />
<file name="ayanna.jpeg" server="//boc22web6.ad.fau.edu/nit/" local="131975705520000000" remote="131975669520000000" Dst="2" />
<file name="craig.jpeg" server="//boc22web6.ad.fau.edu/nit/" local="131651056820000000" remote="131651020820000000" Dst="2" />
<file name="devon.jpeg" server="//boc22web6.ad.fau.edu/nit/" local="131651056740000000" remote="131651020740000000" Dst="2" />
<file name="divyang.jpeg" server="//boc22web6.ad.fau.edu/nit/" local="131677841000000000" remote="131677805000000000" Dst="2" />
<file name="jony.jpg" server="//boc22web6.ad.fau.edu/nit/" local="131651055960000000" remote="131651019960000000" Dst="2" />
<file name="lu.jpg" server="//boc22web6.ad.fau.edu/nit/" local="132150330940000000" remote="132150294940000000" Dst="2" />
<file name="pablo.png" server="//boc22web6.ad.fau.edu/nit/" local="131653517600000000" remote="131653481600000000" Dst="2" />
<file name="ronald.jpg" server="//boc22web6.ad.fau.edu/nit/" local="131931636240000000" remote="131931600240000000" Dst="2" />
<file name="rong.jpg" server="//boc22web6.ad.fau.edu/nit/" local="131975737040000000" remote="131975701040000000" Dst="2" />
</dwsync>