<?xml version="1.0" encoding="utf-8" ?>
<dwsync>
<file name="icon-bottomArrow.png" server="//FAUWEB6.fau.edu/nurnet/" local="131431578920000000" remote="131431614920000000" Dst="1" />
<file name="icon-leftArrow.png" server="//FAUWEB6.fau.edu/nurnet/" local="131428927160000000" remote="131428963160000000" Dst="1" />
<file name="icon-list.png" server="//FAUWEB6.fau.edu/nurnet/" local="131469550540000000" remote="131469586540000000" Dst="1" />
<file name="icon-rightArrow.png" server="//FAUWEB6.fau.edu/nurnet/" local="131428927120000000" remote="131428963120000000" Dst="1" />
<file name="icon-topArrow.png" server="//FAUWEB6.fau.edu/nurnet/" local="131431578920000000" remote="131431614920000000" Dst="1" />
<file name="icon-zoomIn.png" server="//FAUWEB6.fau.edu/nurnet/" local="131468454240000000" remote="131468490240000000" Dst="1" />
<file name="icon-zoomOut.png" server="//FAUWEB6.fau.edu/nurnet/" local="131468454140000000" remote="131468490140000000" Dst="1" />
<file name="icon_cross_big.png" server="//FAUWEB6.fau.edu/nurnet/" local="131428912240000000" remote="131428948240000000" Dst="1" />
<file name="icon_cross_middle.png" server="//FAUWEB6.fau.edu/nurnet/" local="131428912200000000" remote="131428948200000000" Dst="1" />
<file name="icon_cross_small.png" server="//FAUWEB6.fau.edu/nurnet/" local="131428896980000000" remote="131428932980000000" Dst="1" />
<file name="icon_tree_down_arrow.png" server="//FAUWEB6.fau.edu/nurnet/" local="131448819300000000" remote="131448855300000000" Dst="1" />
<file name="icon_tree_up_arrow.png" server="//FAUWEB6.fau.edu/nurnet/" local="131448819720000000" remote="131448855720000000" Dst="1" />
<file name="icon-bottomArrow.png" server="//boc22web6.ad.fau.edu/nit/" local="131431614920000000" remote="131431578920000000" Dst="2" />
<file name="icon-leftArrow.png" server="//boc22web6.ad.fau.edu/nit/" local="131428963160000000" remote="131428927160000000" Dst="2" />
<file name="icon-list.png" server="//boc22web6.ad.fau.edu/nit/" local="131469586540000000" remote="131469550540000000" Dst="2" />
<file name="icon-rightArrow.png" server="//boc22web6.ad.fau.edu/nit/" local="131428963120000000" remote="131428927120000000" Dst="2" />
<file name="icon-topArrow.png" server="//boc22web6.ad.fau.edu/nit/" local="131431614920000000" remote="131431578920000000" Dst="2" />
<file name="icon-zoomIn.png" server="//boc22web6.ad.fau.edu/nit/" local="131468490240000000" remote="131468454240000000" Dst="2" />
<file name="icon-zoomOut.png" server="//boc22web6.ad.fau.edu/nit/" local="131468490140000000" remote="131468454140000000" Dst="2" />
<file name="icon_cross_big.png" server="//boc22web6.ad.fau.edu/nit/" local="131428948240000000" remote="131428912240000000" Dst="2" />
<file name="icon_cross_middle.png" server="//boc22web6.ad.fau.edu/nit/" local="131428948200000000" remote="131428912200000000" Dst="2" />
<file name="icon_cross_small.png" server="//boc22web6.ad.fau.edu/nit/" local="131428932980000000" remote="131428896980000000" Dst="2" />
<file name="icon_tree_down_arrow.png" server="//boc22web6.ad.fau.edu/nit/" local="131448855300000000" remote="131448819300000000" Dst="2" />
<file name="icon_tree_up_arrow.png" server="//boc22web6.ad.fau.edu/nit/" local="131448855720000000" remote="131448819720000000" Dst="2" />
</dwsync>